[{"city":"Zacata","state":"VA","zip":"22581"},{"city":"Zachary","state":"LA","zip":"70791"},{"city":"Zachow","state":"WI","zip":"54182"},{"city":"Zahl","state":"ND","zip":"58856"},{"city":"Zaleski","state":"OH","zip":"45698"},{"city":"Zalma","state":"MO","zip":"63787"},{"city":"Zamora","state":"CA","zip":"95698"},{"city":"Zanesfield","state":"OH","zip":"43360"},{"city":"Zanesville","state":"OH","zip":"43701"},{"city":"Zanesville","state":"OH","zip":"43702"},{"city":"Zanesville","state":"IN","zip":"46799"},{"city":"Zanoni","state":"MO","zip":"65784"},{"city":"Zap","state":"ND","zip":"58580"},{"city":"Zapata","state":"TX","zip":"78076"},{"city":"Zarephath","state":"NJ","zip":"08890"},{"city":"Zavalla","state":"TX","zip":"75980"},{"city":"Zearing","state":"IA","zip":"50278"},{"city":"Zebulon","state":"NC","zip":"27597"},{"city":"Zebulon","state":"GA","zip":"30295"},{"city":"Zeeland","state":"MI","zip":"49464"},{"city":"Zeeland","state":"ND","zip":"58581"},{"city":"Zeigler","state":"IL","zip":"62999"},{"city":"Zelienople","state":"PA","zip":"16063"},{"city":"Zellwood","state":"FL","zip":"32798"},{"city":"Zenda","state":"WI","zip":"53195"},{"city":"Zenda","state":"KS","zip":"67159"},{"city":"Zenia","state":"CA","zip":"95595"},{"city":"Zephyr","state":"TX","zip":"76890"},{"city":"Zephyr Cove","state":"NV","zip":"89448"},{"city":"Zephyrhills","state":"FL","zip":"33539"},{"city":"Zephyrhills","state":"FL","zip":"33540"},{"city":"Zephyrhills","state":"FL","zip":"33541"},{"city":"Zephyrhills","state":"FL","zip":"33542"},{"city":"Zieglerville","state":"PA","zip":"19492"},{"city":"Zillah","state":"WA","zip":"98953"},{"city":"Zimmerman","state":"MN","zip":"55398"},{"city":"Zion","state":"IL","zip":"60099"},{"city":"Zion Grove","state":"PA","zip":"17985"},{"city":"Zionhill","state":"PA","zip":"18981"},{"city":"Zionsville","state":"PA","zip":"18092"},{"city":"Zionsville","state":"IN","zip":"46077"},{"city":"Zionville","state":"NC","zip":"28698"},{"city":"Zirconia","state":"NC","zip":"28790"},{"city":"Zoar","state":"OH","zip":"44697"},{"city":"Zoe","state":"KY","zip":"41397"},{"city":"Zolfo Springs","state":"FL","zip":"33890"},{"city":"Zortman","state":"MT","zip":"59546"},{"city":"Zullinger","state":"PA","zip":"17272"},{"city":"Zumbro Falls","state":"MN","zip":"55991"},{"city":"Zumbrota","state":"MN","zip":"55992"},{"city":"Zuni","state":"VA","zip":"23898"},{"city":"Zuni","state":"NM","zip":"87327"},{"city":"Zurich","state":"MT","zip":"59547"},{"city":"Zwingle","state":"IA","zip":"52079"},{"city":"Zwolle","state":"LA","zip":"71486"}]